ROPGadget-7.7.data/scripts/ROPgadget
ropgadget/__init__.py
ropgadget/args.py
ropgadget/binary.py
ropgadget/core.py
ropgadget/gadgets.py
ropgadget/options.py
ropgadget/rgutils.py
ropgadget/updateAlert.py
ropgadget/version.py
ropgadget/loaders/__init__.py
ropgadget/loaders/elf.py
ropgadget/loaders/macho.py
ropgadget/loaders/pe.py
ropgadget/loaders/raw.py
ropgadget/loaders/universal.py
ropgadget/ropchain/__init__.py
ropgadget/ropchain/ropmaker.py
ropgadget/ropchain/arch/__init__.py
ropgadget/ropchain/arch/ropmakerx64.py
ropgadget/ropchain/arch/ropmakerx86.py
ROPGadget-7.7.dist-info/AUTHORS
ROPGadget-7.7.dist-info/LICENSE_BSD.txt
ROPGadget-7.7.dist-info/METADATA
ROPGadget-7.7.dist-info/WHEEL
ROPGadget-7.7.dist-info/top_level.txt
ROPGadget-7.7.dist-info/RECORD
