Metadata-Version: 2.1
Name: ROPGadget
Version: 7.7
Summary: This tool lets you search your gadgets on your binaries to facilitate your ROP exploitation.
Home-page: https://github.com/JonathanSalwan/ROPgadget
Author: Jonathan Salwan
Author-email: jonathan.salwan@gmail.com
License: BSD
Platform: UNKNOWN
Classifier: Topic :: Security
Classifier: Environment :: Console
Classifier: Operating System :: OS Independent
Classifier: License :: OSI Approved :: BSD License
Classifier: Programming Language :: Python :: 2.7
Classifier: Programming Language :: Python :: 3
Classifier: Intended Audience :: Developers
Requires-Dist: capstone (>=5.0.1)
